Metadata-Version: 2.1
Name: sapphirus
Version: 0.1.0
Summary: Transform your terminal into a canvas of colors with Sapphirus.
Home-page: https://github.com/ekinpy/sapphirus
Author: Ekin Aksu
License: MIT License
Keywords: terminal,style,color,coloring,cli,colors
Classifier: Development Status :: 5 - Production/Stable
Classifier: Environment :: Console
Classifier: Intended Audience :: Developers
Classifier: Programming Language :: Python :: 3
Classifier: Programming Language :: Python :: 3.8
Classifier: Programming Language :: Python :: 3.9
Classifier: Programming Language :: Python :: 3.10
Classifier: Programming Language :: Python :: 3.11
License-File: LICENSE
